.dockerignore
.editorconfig
.gitignore
CONTRIBUTING.md
Dockerfile
LICENSE
MANIFEST.in
Makefile
README.md
pylintrc
pyproject.toml
tox.ini
.github/dependabot.yml
.github/stale.yml
.github/workflows/codeql-analysis.yml
.github/workflows/tests.yml
docs/Makefile
docs/requirements.txt
docs/source/changelog.rst
docs/source/conf.py
docs/source/index.rst
docs/source/modules.rst
docs/source/non_blocking_login.rst
docs/source/proxy.rst
docs/source/tdlib.rst
docs/source/telegram.rst
docs/source/tutorial.rst
docs/source/_templates/about.html
docs/source/_templates/navigation.html
examples/bot_login.py
examples/chat_stats.py
examples/clear_group_messages.py
examples/echo_bot.py
examples/get_instant_view.py
examples/get_me.py
examples/get_me_non_blocking_login.py
examples/send_message.py
examples/utils.py
python_telegram.egg-info/PKG-INFO
python_telegram.egg-info/SOURCES.txt
python_telegram.egg-info/dependency_links.txt
python_telegram.egg-info/not-zip-safe
python_telegram.egg-info/requires.txt
python_telegram.egg-info/top_level.txt
telegram/__init__.py
telegram/_version.py
telegram/client.py
telegram/py.typed
telegram/tdjson.py
telegram/text.py
telegram/utils.py
telegram/worker.py
telegram/lib/darwin/libtdjson.dylib
telegram/lib/linux/libtdjson.so
tests/__init__.py
tests/requirements.txt
tests/test_tdjson.py
tests/test_telegram_methods.py
tests/test_utils.py