Metadata-Version: 2.1
Name: python-telegram
Version: 0.19.0
Summary: Python library to help you build your own Telegram clients
Author-email: Alexander Akhmetov <me@alx.cx>
License: MIT
Project-URL: Source, https://github.com/alexander-akhmetov/python-telegram
Project-URL: Documentation, https://python-telegram.readthedocs.io/en/latest/
Project-URL: Tutorial, https://python-telegram.readthedocs.io/en/latest/tutorial.html
Project-URL: Changelog, https://python-telegram.readthedocs.io/en/latest/changelog.html
Keywords: telegram,client,api,tdlib,tdjson,td
Classifier: Intended Audience :: Developers
Classifier: License :: OSI Approved :: MIT License
Classifier: Operating System :: MacOS :: MacOS X
Classifier: Operating System :: POSIX :: Linux
Classifier: Programming Language :: Python :: 3.9
Classifier: Programming Language :: Python :: 3.10
Classifier: Programming Language :: Python :: 3.11
Classifier: Programming Language :: Python :: 3.12
Classifier: Programming Language :: Python :: 3 :: Only
Classifier: Topic :: Software Development :: Libraries :: Python Modules
Requires-Python: >=3.9
License-File: LICENSE
Requires-Dist: telegram-text==0.2.0
